multi_stage_sync/sync3_stage.v
module sync3_stage (
 input wire clk,
 input wire async_in,
 output reg sync_out );
 reg sync_ff1, sync_ff2;
 always @(posedge clk) begin
 sync_ff1 <= async_in;
 sync_ff2 <= sync_ff1;
 sync_out <= sync_ff2;
 end
endmodule

multi_stage_sync/sync2_stage.v
module sync2_stage (
 input wire clk,
 input wire async_in,
 output reg sync_out
);
 reg sync_ff1;
 always @(posedge clk) begin
 sync_ff1 <= async_in; // First stage
 sync_out <= sync_ff1; // Second stage
 end
endmodule

multi_stage_sync/sync_tb.v
`timescale 1ns / 1ps

module sync_tb;

    // -------------------------------------------------
    // Testbench signals
    // -------------------------------------------------
    reg  clk;
    reg  async_in;

    wire sync_out2;
    wire sync_out3;

    // -------------------------------------------------
    // Clock generation
    // 10 ns period (100 MHz)
    // -------------------------------------------------
    initial begin
        clk = 1'b0;
        forever #5 clk = ~clk;
    end

    // -------------------------------------------------
    // 2-stage synchronizer
    // -------------------------------------------------
    sync2_stage u_sync2 (
        .clk      (clk),
        .async_in (async_in),
        .sync_out (sync_out2)
    );

    // -------------------------------------------------
    // 3-stage synchronizer
    // -------------------------------------------------
    sync3_stage u_sync3 (
        .clk      (clk),
        .async_in (async_in),
        .sync_out (sync_out3)
    );

    // -------------------------------------------------
    // Test stimulus
    // -------------------------------------------------
    initial begin
        // Initial values
        async_in = 1'b0;

        // Allow the design to initialize
        #20;

        // Asynchronous pulse 1
        #3;
        async_in = 1'b1;

        #15;
        async_in = 1'b0;

        // Asynchronous pulse 2
        #25;
        async_in = 1'b1;

        #30;
        async_in = 1'b0;

        // Allow outputs to settle
        #50;

        // End simulation
        $finish;
    end

    // -------------------------------------------------
    // VCD waveform dump
    // Compatible with GTKWave
    // -------------------------------------------------
    initial begin
        $dumpfile("sync_tb.vcd");
        $dumpvars(0, sync_tb);
    end

endmodule

multi_stage_sync/sync_tb.vcd
$date
	Thu Sep 17 16:33:55 2026
$end
$version
	Icarus Verilog
$end
$timescale
	1ps
$end
$scope module sync_tb $end
$var wire 1 ! sync_out3 $end
$var wire 1 " sync_out2 $end
$var reg 1 # async_in $end
$var reg 1 $ clk $end
$scope module u_sync2 $end
$var wire 1 # async_in $end
$var wire 1 $ clk $end
$var reg 1 % sync_ff1 $end
$var reg 1 " sync_out $end
$upscope $end
$scope module u_sync3 $end
$var wire 1 # async_in $end
$var wire 1 $ clk $end
$var reg 1 & sync_ff1 $end
$var reg 1 ' sync_ff2 $end
$var reg 1 ! sync_out $end
$upscope $end
$upscope $end
$enddefinitions $end
$comment Show the parameter values. $end
$dumpall
$end
#0
$dumpvars
x'
x&
x%
0$
0#
x"
x!
$end
#5000
0%
0&
1$
#10000
0$
#15000
0'
0"
1$
#20000
0$
#23000
1#
#25000
1%
0!
1&
1$
#30000
0$
#35000
1'
1"
1$
#38000
0#
#40000
0$
#45000
0%
1!
0&
1$
#50000
0$
#55000
0'
0"
1$
#60000
0$
#63000
1#
#65000
1%
0!
1&
1$
#70000
0$
#75000
1'
1"
1$
#80000
0$
#85000
1!
1$
#90000
0$
#93000
0#
#95000
0&
0%
1$
#100000
0$
#105000
0"
0'
1$
#110000
0$
#115000
0!
1$
